{
  "date": "2026-02-01",
  "source_url": "https://m.liveonsat.com/2day.php",
  "matches": [
    {
      "competition": "Dutch Eredivisie - Week 21",
      "title": "PSV Eindhoven v Feyenoord",
      "kickoff_baghdad": "07:30",
      "channels_raw": [
        "Arena Sport 1 Slovakia HD",
        "Dubai Sports 2 HD",
        "ESPN 2 Nederland HD",
        "ESPN Extra Nederland",
        "ESPN+ USA ($/geo/R)",
        "Premier Sports GB Player HD",
        "S Sport+ Streaming",
        "Setanta Sports Premium HD",
        "Sport 4 Israel HD",
        "Sportdigital FUSSBALL HD",
        "Thriller TV+ [online] ($/geo/R)",
        "Tivibu Spor HD",
        "Discover more",
        "Training equipment",
        "Live Soccer TV",
        "FIFA video games",
        "Dutch Eredivisie - Week 21"
      ]
    },
    {
      "competition": "Dutch Eredivisie - Week 21",
      "title": "Heracles Almelo v Fortuna Sittard",
      "kickoff_baghdad": "07:30",
      "channels_raw": [
        "ESPN 1 Nederland HD",
        "ESPN Extra Nederland",
        "Discover more",
        "Womens Football Gear",
        "Youth Soccer Equipment",
        "Travel packages",
        "Scottish SWPL Cup - Semi Final"
      ]
    },
    {
      "competition": "Dutch Eredivisie - Week 21",
      "title": "Rangers v Celtic",
      "kickoff_baghdad": "07:40",
      "channels_raw": [
        "BBC Alba HD",
        "BBC iPlayer (geo/R)",
        "BBC iPlayer 4K (geo/R)",
        "BBC Sport Scotland Online",
        "Discover more",
        "Football coaching courses",
        "Football boots",
        "Sports news subscriptions",
        "Polish Ekstraklasa - Week 19"
      ]
    },
    {
      "competition": "Dutch Eredivisie - Week 21",
      "title": "Wisla Plock v Raków Czestochowa",
      "kickoff_baghdad": "07:45",
      "channels_raw": [
        "Canal+ Sport 3 Polska HD",
        "Ekstraklasa TV ($/PPV)",
        "Discover more",
        "Bundesliga Fan Gear",
        "Stadium tours",
        "Fernsehen",
        "Croatian HNL - Week 20"
      ]
    },
    {
      "competition": "Dutch Eredivisie - Week 21",
      "title": "Osijek v Rijeka",
      "kickoff_baghdad": "08:00",
      "channels_raw": [
        "MAX Sport 1 Hrvatska HD",
        "Discover more",
        "Sports Streaming Service",
        "Deportes",
        "Europa League Tickets",
        "Cypriot 1. Division - Week 20"
      ]
    },
    {
      "competition": "Dutch Eredivisie - Week 21",
      "title": "Omonia Nicosia v Krasava FC",
      "kickoff_baghdad": "08:00",
      "channels_raw": [
        "Cytavision Sports 1 HD",
        "Discover more",
        "Spor",
        "Sports memorabilia",
        "Soccer balls",
        "English Premier League - Week 24"
      ]
    },
    {
      "competition": "Dutch Eredivisie - Week 21",
      "title": "Manchester United v Fulham",
      "kickoff_baghdad": "08:00",
      "channels_raw": [
        "beIN Connect MENA",
        "beIN Connect Türkiye",
        "beIN Sports MENA 1 HD",
        "beIN Sports MENA English 1 HD",
        "beIN Sports Türkiye 3 HD",
        "Canal+ Foot HD",
        "Canal+ Live 1 France HD",
        "Canal+ Sport 1 Czech HD",
        "Cytavision Sports 3 HD",
        "DAZN 1 Bar Espana",
        "DAZN 1 Espana HD",
        "DAZN 1 Portugal HD",
        "DAZN España ($/geo/R)",
        "FuboTV Canada ($/geo/R)",
        "Go3 Extra Sport Baltics ($/geo/R)",
        "Hub Premier 1 HD ($/geo/R)",
        "Hub Premier 4 HD ($/geo/R)",
        "Monomax Streaming ($/geo/R)",
        "NBC Sports Network",
        "Nova Sports Premier League HD",
        "Peacock Premium USA ($/geo/R)",
        "Sky Go UK [online]",
        "Sky Sports Main Event HD",
        "Sky Sports Main Event UHD",
        "Sky UK Ultra HD 1",
        "Solh TV",
        "Sport 1 Israel HD",
        "Sport 24 At Sea HD",
        "Sport 24 In Flight HD",
        "Sport TV Azerbaijan (geo/R)",
        "Stan Sport Australia ($/geo/R)",
        "Star Sports Select HD1",
        "TV3+ Dansk HD"
      ]
    },
    {
      "competition": "Dutch Eredivisie - Week 21",
      "title": "V Sport Premier League 1 HD",
      "kickoff_baghdad": null,
      "channels_raw": [
        "Varzish TV Sport HD (tjk)",
        "ViaPlay Danmark HD",
        "ViaPlay Nederland HD",
        "ViaPlay Norge HD",
        "ViaPlay Suomi HD",
        "ViaPlay Sverige HD",
        "VOYO Pro TV Romania [$]",
        "Discover more",
        "Team scarves",
        "Football kits",
        "FIFA+ [app",
        "English Premier League - Week 24"
      ]
    },
    {
      "competition": "Dutch Eredivisie - Week 21",
      "title": "Nottingham Forest v Crystal Palace",
      "kickoff_baghdad": "08:00",
      "channels_raw": [
        "beIN Connect MENA",
        "beIN Connect Türkiye",
        "beIN Sports MENA 8 HD",
        "Canal+ Live 2 France HD",
        "Canal+ Sport 6 Czech HD",
        "Canal+ Sport France HD",
        "DAZN España ($/geo/R)",
        "FuboTV Canada ($/geo/R)",
        "Go3 Extra Sport Baltics ($/geo/R)",
        "Hub Premier 3 HD ($/geo/R)",
        "Monomax Streaming ($/geo/R)",
        "Nova Sports 4 Hellas HD",
        "Peacock Premium USA ($/geo/R)",
        "Sky Sports+ [via APP]",
        "Sky Sports+ TV HD",
        "Stan Sport Australia ($/geo/R)",
        "TV3 Sport Dansk HD",
        "ViaPlay Danmark HD",
        "ViaPlay Nederland HD",
        "ViaPlay Norge HD",
        "ViaPlay Suomi HD",
        "ViaPlay Sverige HD",
        "VOYO Pro TV Romania [$]",
        "Discover more",
        "Fan apparel",
        "Boxing Fitness Gear",
        "Streaming Device Deals",
        "English Premier League - Week 24"
      ]
    },
    {
      "competition": "Dutch Eredivisie - Week 21",
      "title": "Aston Villa v Brentford",
      "kickoff_baghdad": "08:00",
      "channels_raw": [
        "beIN Connect MENA",
        "beIN Connect Türkiye",
        "beIN Sports MENA 4 HD",
        "beIN Sports Türkiye 4 HD",
        "Canal+ Live 3 France HD",
        "Canal+ Sport 360 HD",
        "Canal+ Sport 5 Czech HD",
        "DAZN España ($/geo/R)",
        "FuboTV Canada ($/geo/R)",
        "Go3 Extra Sport Baltics ($/geo/R)",
        "Hub Premier 2 HD ($/geo/R)",
        "Monomax Streaming ($/geo/R)",
        "Nova Sports 5 Hellas HD",
        "Sky Go UK [online]",
        "Sky Sports Premier League HD",
        "Sport 3 Israel HD",
        "Stan Sport Australia ($/geo/R)",
        "Telemundo USA",
        "TV3 MAX Dansk HD",
        "USA Network HD",
        "ViaPlay Danmark HD",
        "ViaPlay Nederland HD",
        "ViaPlay Norge HD",
        "ViaPlay Suomi HD",
        "ViaPlay Sverige HD",
        "VOYO Pro TV Romania [$]",
        "Discover more",
        "Sport",
        "Ligue 1 Jerseys",
        "Ice Hockey Jerseys",
        "English WSL 2 - Week 14"
      ]
    },
    {
      "competition": "Dutch Eredivisie - Week 21",
      "title": "Birmingham City v Nottingham Forest",
      "kickoff_baghdad": "08:00",
      "channels_raw": [
        "YouTube: W/Super League 2",
        "English WSL 2 - Week 14"
      ]
    },
    {
      "competition": "Dutch Eredivisie - Week 21",
      "title": "Newcastle United v Ipswich Town",
      "kickoff_baghdad": "08:00",
      "channels_raw": [
        "YouTube: W/Super League 2",
        "Discover more",
        "Sports TV Guide",
        "Television",
        "TV",
        "English WSL 2 - Week 14"
      ]
    },
    {
      "competition": "Dutch Eredivisie - Week 21",
      "title": "Southampton v Crystal Palace",
      "kickoff_baghdad": "08:00",
      "channels_raw": [
        "YouTube: W/Super League 2",
        "Discover more",
        "Soccer Match Schedules",
        "Baseball Memorabilia",
        "American Sports Apparel",
        "French Féminine Première Ligue - Week 14"
      ]
    },
    {
      "competition": "Dutch Eredivisie - Week 21",
      "title": "Paris St Germain v Lyon",
      "kickoff_baghdad": "08:00",
      "channels_raw": [
        "DAZN Great Britain (geo/R)",
        "DAZN Ireland ($/geo/R)",
        "Discover more",
        "Sports commentary books",
        "La Liga Subscription",
        "Football jerseys",
        "French Ligue 1 - Week 20"
      ]
    },
    {
      "competition": "Dutch Eredivisie - Week 21",
      "title": "Lyon v Lille",
      "kickoff_baghdad": "08:00",
      "channels_raw": [
        "beIN Connect MENA",
        "beIN Connect Türkiye",
        "beIN Connect USA",
        "beIN Sports MENA 6 HD",
        "beIN Sports Türkiye Max 1 HD",
        "DAZN France ($/geo/R)",
        "Fanatiz USA ($/geo/R)",
        "Fubo Sports USA ($/geo/R)",
        "Ligue 1+ ($/geo/R)",
        "Prime Video UK PPV [$]",
        "Sport TV 2 Azerbaijan (geo/R)",
        "ViaPlay Danmark HD",
        "ViaPlay Nederland HD",
        "ViaPlay Norge HD",
        "ViaPlay Suomi HD",
        "ViaPlay Sverige HD",
        "Discover more",
        "Champions League Merch",
        "Sports",
        "Sports betting guides",
        "Greek Super League 1 - Week 19"
      ]
    },
    {
      "competition": "Dutch Eredivisie - Week 21",
      "title": "Levadiakos v Asteras Tripolis",
      "kickoff_baghdad": "08:00",
      "channels_raw": [
        "Nova Sports Prime Cyprus HD",
        "Nova Sports Prime Hellas HD",
        "Discover more",
        "World Cup tickets",
        "Team merchandise",
        "FIFA+ Stream Live Football TV",
        "Italian Serie A - Week 23"
      ]
    },
    {
      "competition": "Dutch Eredivisie - Week 21",
      "title": "Como v Atalanta",
      "kickoff_baghdad": "08:00",
      "channels_raw": [
        "beIN Sports Australia 3 HD",
        "Cosmote Sport 2 HD",
        "DAZN Belgium ($/geo/R)",
        "DAZN Great Britain (geo/R)",
        "DAZN Ireland ($/geo/R)",
        "DAZN Italia ($/geo/R)",
        "DAZN USA en Español ($/geo/R)",
        "Paramount+ USA ($/geo/R)",
        "S Sport 2 Türkiye HD",
        "S Sport+ Streaming",
        "Sport 2 Israel HD",
        "Tivibu Spor 1 HD",
        "Tring Sport 1 HD",
        "Ziggo Sport 2",
        "Italian Serie BKT - Week 22"
      ]
    },
    {
      "competition": "Dutch Eredivisie - Week 21",
      "title": "Reggiana v Juve Stabia",
      "kickoff_baghdad": "08:00",
      "channels_raw": [
        "OneFootball [app] ($/geo/R)",
        "Italian W/Serie A - Week 12"
      ]
    },
    {
      "competition": "Dutch Eredivisie - Week 21",
      "title": "Ternana v Inter Milan",
      "kickoff_baghdad": "08:00",
      "channels_raw": [
        "DAZN Italia ($/geo/R)",
        "Italian W/Serie A - Week 12"
      ]
    },
    {
      "competition": "Dutch Eredivisie - Week 21",
      "title": "Parma v Roma",
      "kickoff_baghdad": "08:00",
      "channels_raw": [
        "DAZN Italia ($/geo/R)",
        "Scottish Premiership - Week 24"
      ]
    },
    {
      "competition": "Dutch Eredivisie - Week 21",
      "title": "Hibernian v Rangers",
      "kickoff_baghdad": "08:00",
      "channels_raw": [
        "5 STARS Israel HD",
        "Hibs TV ($/geo/R)",
        "Premier Sports 1 Ireland HD",
        "Premier Sports 1 UK HD",
        "Premier Sports GB Player HD",
        "Rangers TV ($/geo/R)",
        "S Sport+ Streaming",
        "Türkiye Süper Lig - Week 20"
      ]
    },
    {
      "competition": "Dutch Eredivisie - Week 21",
      "title": "Gençlerbirligi v Gaziantep",
      "kickoff_baghdad": "08:00",
      "channels_raw": [
        "beIN Connect Türkiye",
        "beIN Sports Türkiye 1 HD",
        "Azerbaijan Premier League - Week 18"
      ]
    },
    {
      "competition": "Dutch Eredivisie - Week 21",
      "title": "Qarabagh v Turan",
      "kickoff_baghdad": "08:30",
      "channels_raw": [
        "CBC Sport HD",
        "English Womens Super League - Week 14"
      ]
    },
    {
      "competition": "Dutch Eredivisie - Week 21",
      "title": "Manchester City v Chelsea",
      "kickoff_baghdad": "08:30",
      "channels_raw": [
        "BBC iPlayer (geo/R)",
        "BBC iPlayer 4K (geo/R)",
        "BBC One HD",
        "BBC Sport Website (geo/R)",
        "Star Sports Select HD1",
        "W-Sport HD",
        "German 1. Bundesliga - Week 20"
      ]
    },
    {
      "competition": "Dutch Eredivisie - Week 21",
      "title": "Stuttgart v Freiburg",
      "kickoff_baghdad": "08:45",
      "channels_raw": [
        "beIN Sports France 4 HD max",
        "DAZN Deutsch ($/geo/R)",
        "DAZN Japan ($/geo/R)",
        "ESPN+ USA ($/geo/R)",
        "Okko Futbol HD ($/geo/R)",
        "OneFootball [app] ($/geo/R)",
        "Prime Video UK PPV [$]",
        "S Sport+ Streaming",
        "Tivibu Spor 2 HD",
        "TV2 Play Norge ($/geo/R)",
        "ViaPlay Danmark HD",
        "ViaPlay Nederland HD",
        "ViaPlay Norge HD",
        "ViaPlay Suomi HD",
        "ViaPlay Sverige HD",
        "ViaPlay Ísland HD",
        "FIFA Womens Champions Cup - 3rd Place Play-Off",
        "** T.B.D. **",
        "Sky Go UK [online]",
        "Sky Sports Football HD",
        "Belgian Pro League - Week 23"
      ]
    },
    {
      "competition": "Dutch Eredivisie - Week 21",
      "title": "Dender v Racing Genk",
      "kickoff_baghdad": "09:00",
      "channels_raw": [
        "DAZN Belgium ($/geo/R)",
        "DAZN Pro League 2 HD",
        "Cypriot 1. Division - Week 20"
      ]
    },
    {
      "competition": "Dutch Eredivisie - Week 21",
      "title": "Akritas Chlorakas v Anorthosis",
      "kickoff_baghdad": "09:00",
      "channels_raw": [
        "Cytavision Sports 2 HD",
        "German Frauen Bundesliga - Week 16"
      ]
    },
    {
      "competition": "Dutch Eredivisie - Week 21",
      "title": "Hoffenheim v Werder Bremen",
      "kickoff_baghdad": "09:00",
      "channels_raw": [
        "DAZN Deutsch ($/geo/R)",
        "DAZN Great Britain (geo/R)",
        "DAZN Ireland ($/geo/R)",
        "Magenta Sport ($/geo/R)",
        "Scottish Premiership - Week 24"
      ]
    },
    {
      "competition": "Dutch Eredivisie - Week 21",
      "title": "Celtic v Falkirk",
      "kickoff_baghdad": "09:00",
      "channels_raw": [
        "Celtic TV ($/geo/R)",
        "Falkirk TV [$]",
        "Romanian Superliga - Week 24"
      ]
    },
    {
      "competition": "Dutch Eredivisie - Week 21",
      "title": "Farul Constanta v Universitatea Craiova",
      "kickoff_baghdad": "09:15",
      "channels_raw": [
        "Digi Sport 1 Romania HD",
        "Prima Sport RO 1 HD",
        "Saudi Pro League - Week 20"
      ]
    },
    {
      "competition": "Dutch Eredivisie - Week 21",
      "title": "Al Shabab v Al Fayha",
      "kickoff_baghdad": "09:15",
      "channels_raw": [
        "Thmanyah KSA [app]",
        "Spanish La Liga (Primera) - Week 22"
      ]
    },
    {
      "competition": "Dutch Eredivisie - Week 21",
      "title": "Real Betis v Valencia",
      "kickoff_baghdad": "09:15",
      "channels_raw": [
        "beIN Connect MENA",
        "beIN Sports Australia 2 HD",
        "beIN Sports MENA 5 HD",
        "beIN Sports MENA English 2 HD",
        "DAZN 2 Portugal HD",
        "DAZN Belgium ($/geo/R)",
        "DAZN Deutsch ($/geo/R)",
        "DAZN Italia ($/geo/R)",
        "DAZN USA en Español ($/geo/R)",
        "ESPN Deportes",
        "ESPN+ USA ($/geo/R)",
        "Fast Sports [online] ($/geo/R)",
        "Fubo Sports USA ($/geo/R)",
        "LaLiga TV Bar HD",
        "M+ LaLiga HD",
        "M+ LaLiga HDR",
        "Movistar Plus+ HD",
        "MTV Katsomon+ ($/geo/R)",
        "ONE Sport Israel HD",
        "Orange Fútbol 1 HD",
        "Premier Sports 2 Ireland HD",
        "Premier Sports 2 UK HD",
        "Premier Sports GB Player HD",
        "S Sport 1 Türkiye HD",
        "S Sport+ Streaming",
        "TSN+ Canada ($/geo/R)",
        "TV2 Play Danmark ($/geo/R)",
        "TV2 Play Norge ($/geo/R)",
        "TV4 Play Sverige [online]",
        "ViaPlay Norge HD",
        "Ziggo Sport HD",
        "Albanian Superliga - Week 22"
      ]
    },
    {
      "competition": "Dutch Eredivisie - Week 21",
      "title": "Egnatia v KF Tirana",
      "kickoff_baghdad": "09:30",
      "channels_raw": [
        "FIFA+ [app] (geo/R)",
        "RTSH Tani [app]",
        "Albanian Superliga - Week 22"
      ]
    },
    {
      "competition": "Dutch Eredivisie - Week 21",
      "title": "Teuta v Vllaznia Shkodër",
      "kickoff_baghdad": "09:30",
      "channels_raw": [
        "FIFA+ [app] (geo/R)",
        "RTSH Tani [app]",
        "German 3. Liga - Week 22"
      ]
    },
    {
      "competition": "Dutch Eredivisie - Week 21",
      "title": "SC Verl v Stuttgart II",
      "kickoff_baghdad": "09:30",
      "channels_raw": [
        "Magenta Sport ($/geo/R)",
        "OneFootball [app] ($/geo/R)",
        "Greek Super League 1 - Week 19"
      ]
    },
    {
      "competition": "Dutch Eredivisie - Week 21",
      "title": "Panathinaikos v Kifisia",
      "kickoff_baghdad": "09:30",
      "channels_raw": [
        "Cosmote Sport 1 HD",
        "Portuguese Liga Portugal - Week 20"
      ]
    },
    {
      "competition": "Dutch Eredivisie - Week 21",
      "title": "Gil Vicente v Famalicão",
      "kickoff_baghdad": "09:30",
      "channels_raw": [
        "Megogo Sport Kazakhstan [$]",
        "Sport TV1 Portugal HD",
        "Spanish Liga F Femenino - Week 18"
      ]
    },
    {
      "competition": "Dutch Eredivisie - Week 21",
      "title": "Barcelona v Sevilla",
      "kickoff_baghdad": "09:30",
      "channels_raw": [
        "DAZN España ($/geo/R)",
        "DAZN Great Britain (geo/R)",
        "DAZN Ireland ($/geo/R)",
        "Swiss Super League - Week 22"
      ]
    },
    {
      "competition": "Dutch Eredivisie - Week 21",
      "title": "Basel v Thun",
      "kickoff_baghdad": "09:30",
      "channels_raw": [
        "Sport 1 Baltic",
        "Sport 1 Ukraine",
        "SuperSport 6 Albania HD",
        "Dutch Eredivisie - Week 21"
      ]
    },
    {
      "competition": "Dutch Eredivisie - Week 21",
      "title": "Heerenveen v Utrecht",
      "kickoff_baghdad": "09:45",
      "channels_raw": [
        "ESPN 3 Nederland HD",
        "ESPN Extra Nederland",
        "Dutch Vrouwen Eredivisie - Week 13"
      ]
    },
    {
      "competition": "Dutch Eredivisie - Week 21",
      "title": "Heerenveen v ADO Den Haag",
      "kickoff_baghdad": "09:45",
      "channels_raw": [
        "ESPN 1 Nederland HD",
        "Dutch Vrouwen Eredivisie - Week 13"
      ]
    },
    {
      "competition": "Dutch Eredivisie - Week 21",
      "title": "Twente v Excelsior",
      "kickoff_baghdad": "09:45",
      "channels_raw": [
        "ESPN Extra Nederland",
        "Dutch Vrouwen Eredivisie - Week 13"
      ]
    },
    {
      "competition": "Dutch Eredivisie - Week 21",
      "title": "Utrecht v NAC Breda",
      "kickoff_baghdad": "09:45",
      "channels_raw": [
        "ESPN Extra Nederland",
        "Dutch Vrouwen Eredivisie - Week 13"
      ]
    },
    {
      "competition": "Dutch Eredivisie - Week 21",
      "title": "Ajax v HERA United",
      "kickoff_baghdad": "09:45",
      "channels_raw": [
        "ESPN Extra Nederland",
        "Dutch Vrouwen Eredivisie - Week 13"
      ]
    },
    {
      "competition": "Dutch Eredivisie - Week 21",
      "title": "Feyenoord v PSV Eindhoven",
      "kickoff_baghdad": "09:45",
      "channels_raw": [
        "ESPN Extra Nederland",
        "CAF African Champions League - Group Stage: Round 4"
      ]
    },
    {
      "competition": "Dutch Eredivisie - Week 21",
      "title": "Rivers United v Power Dynamos",
      "kickoff_baghdad": "10:00",
      "channels_raw": [
        "beIN Sports MENA 3 HD",
        "Türkiye 1. Lig - Week 23"
      ]
    },
    {
      "competition": "Dutch Eredivisie - Week 21",
      "title": "Amedspor v Adana Demirspor",
      "kickoff_baghdad": "10:00",
      "channels_raw": [
        "beIN Connect Türkiye",
        "beIN Sports Türkiye 2 HD",
        "beIN Sports Türkiye Max 1 HD",
        "TRT Spor Türkiye HD",
        "French Ligue 1 - Week 20"
      ]
    },
    {
      "competition": "Dutch Eredivisie - Week 21",
      "title": "Toulouse v Auxerre",
      "kickoff_baghdad": "10:15",
      "channels_raw": [
        "beIN Connect MENA",
        "beIN Connect Türkiye",
        "beIN Connect USA",
        "beIN Sports MENA 8 HD",
        "beIN Sports Türkiye 4 HD",
        "DAZN France ($/geo/R)",
        "Fanatiz USA ($/geo/R)",
        "Fubo Sports USA ($/geo/R)",
        "ViaPlay Danmark HD",
        "ViaPlay Nederland HD",
        "ViaPlay Norge HD",
        "ViaPlay Suomi HD",
        "ViaPlay Sverige HD",
        "French Ligue 1 - Week 20"
      ]
    },
    {
      "competition": "Dutch Eredivisie - Week 21",
      "title": "Nice v Brest",
      "kickoff_baghdad": "10:15",
      "channels_raw": [
        "beIN Connect MENA",
        "beIN Connect Türkiye",
        "beIN Connect USA",
        "beIN Sports MENA 4 HD",
        "beIN Sports Türkiye Max 1 HD",
        "DAZN France ($/geo/R)",
        "Fanatiz USA ($/geo/R)",
        "Fubo Sports USA ($/geo/R)",
        "ViaPlay Danmark HD",
        "ViaPlay Nederland HD",
        "ViaPlay Norge HD",
        "ViaPlay Suomi HD",
        "ViaPlay Sverige HD",
        "French Ligue 1 - Week 20"
      ]
    },
    {
      "competition": "Dutch Eredivisie - Week 21",
      "title": "Angers v Metz",
      "kickoff_baghdad": "10:15",
      "channels_raw": [
        "beIN Connect MENA",
        "beIN Connect Türkiye",
        "beIN Connect USA",
        "beIN Sports MENA 6 HD",
        "DAZN France ($/geo/R)",
        "Fanatiz USA ($/geo/R)",
        "Fubo Sports USA ($/geo/R)",
        "ViaPlay Danmark HD",
        "ViaPlay Nederland HD",
        "ViaPlay Norge HD",
        "ViaPlay Suomi HD",
        "ViaPlay Sverige HD",
        "Italian Serie BKT - Week 22"
      ]
    },
    {
      "competition": "Dutch Eredivisie - Week 21",
      "title": "Padova v Monza",
      "kickoff_baghdad": "10:15",
      "channels_raw": [
        "OneFootball [app] ($/geo/R)",
        "Austrian Cup (ÖFB Cup) - Quarter Final"
      ]
    },
    {
      "competition": "Dutch Eredivisie - Week 21",
      "title": "Wolfsberger AC v Salzburg",
      "kickoff_baghdad": "10:30",
      "channels_raw": [
        "ORF 1 Austria HD [s/cast]",
        "Austrian Cup (ÖFB Cup) - Quarter Final"
      ]
    },
    {
      "competition": "Dutch Eredivisie - Week 21",
      "title": "Rheindorf Altach v Sturm Graz",
      "kickoff_baghdad": "10:30",
      "channels_raw": [
        "ORF 1 Austria HD [s/cast]",
        "English Premier League - Week 24"
      ]
    },
    {
      "competition": "Dutch Eredivisie - Week 21",
      "title": "Tottenham Hotspur v Manchester City",
      "kickoff_baghdad": "10:30",
      "channels_raw": [
        "beIN Connect MENA",
        "beIN Connect Türkiye",
        "beIN Sports MENA 1 HD",
        "beIN Sports MENA English 1 HD",
        "beIN Sports Türkiye 3 HD",
        "Canal+ Foot HD",
        "Canal+ Live 1 France HD",
        "Canal+ Sport 1 Czech HD",
        "Cytavision Sports 3 HD",
        "DAZN 1 Bar Espana",
        "DAZN 1 Espana HD",
        "DAZN 1 Portugal HD",
        "DAZN España ($/geo/R)",
        "FuboTV Canada ($/geo/R)",
        "Go3 Extra Sport Baltics ($/geo/R)",
        "Hub Premier 1 HD ($/geo/R)",
        "Hub Premier 2 HD ($/geo/R)",
        "Hub Premier 8 HD ($/geo/R)",
        "Idman TV HD",
        "Meraj TV",
        "Monomax Streaming ($/geo/R)",
        "NBC Sports Network",
        "Nova Sports Premier League HD",
        "Peacock Premium USA ($/geo/R)",
        "See Dansk HD",
        "Sky Go UK [online]",
        "Sky Sports Main Event HD",
        "Sky Sports Main Event UHD",
        "Sky Sports Premier League HD",
        "Sky UK Ultra HD 1",
        "Solh TV",
        "Sport 1 Israel HD",
        "Sport 24 At Sea HD",
        "Sport 24 In Flight HD",
        "Stan Sport Australia ($/geo/R)"
      ]
    },
    {
      "competition": "Dutch Eredivisie - Week 21",
      "title": "V Sport Premier League HD",
      "kickoff_baghdad": null,
      "channels_raw": [
        "Varzish TV Sport HD (tjk)",
        "ViaPlay Danmark HD",
        "ViaPlay Nederland HD",
        "ViaPlay Norge HD",
        "ViaPlay Suomi HD",
        "ViaPlay Sverige HD",
        "VOYO Pro TV Romania [$]",
        "German 1. Bundesliga - Week 20"
      ]
    },
    {
      "competition": "Dutch Eredivisie - Week 21",
      "title": "Borussia Dortmund v Heidenheim",
      "kickoff_baghdad": "10:30",
      "channels_raw": [
        "beIN Sports France 6 HD max",
        "DAZN Deutsch ($/geo/R)",
        "DAZN Japan ($/geo/R)",
        "ESPN+ USA ($/geo/R)",
        "Okko Futbol HD ($/geo/R)",
        "OneFootball [app] ($/geo/R)",
        "Prime Video UK PPV [$]",
        "S Sport+ Streaming",
        "Sport 2 Israel HD",
        "Tivibu Spor 3 HD",
        "TV2 Play Norge ($/geo/R)",
        "TV3 MAX Dansk HD",
        "ViaPlay Danmark HD",
        "ViaPlay Nederland HD",
        "ViaPlay Norge HD",
        "ViaPlay Suomi HD",
        "ViaPlay Sverige HD",
        "ViaPlay Ísland HD",
        "Polish Ekstraklasa - Week 19"
      ]
    },
    {
      "competition": "Dutch Eredivisie - Week 21",
      "title": "Legia Warsaw v Korona Kielce",
      "kickoff_baghdad": "10:30",
      "channels_raw": [
        "Canal+ Sport 3 Polska HD",
        "Ekstraklasa TV ($/PPV)",
        "Cypriot 1. Division - Week 20"
      ]
    },
    {
      "competition": "Dutch Eredivisie - Week 21",
      "title": "AEL Limassol v Aris Limassol",
      "kickoff_baghdad": "11:00",
      "channels_raw": [
        "Cytavision Sports 1 HD",
        "Italian Serie A - Week 23"
      ]
    },
    {
      "competition": "Dutch Eredivisie - Week 21",
      "title": "Cremonese v Inter Milan",
      "kickoff_baghdad": "11:00",
      "channels_raw": [
        "beIN Sports Australia 3 HD",
        "Cosmote Sport 2 HD",
        "DAZN Belgium ($/geo/R)",
        "DAZN Great Britain (geo/R)",
        "DAZN Ireland ($/geo/R)",
        "DAZN Italia ($/geo/R)",
        "DAZN USA en Español ($/geo/R)",
        "Futbol TV Tajikistan",
        "Paramount+ USA ($/geo/R)",
        "S Sport 2 Türkiye HD",
        "S Sport+ Streaming",
        "Tivibu Spor 1 HD",
        "Tring Sport 1 HD",
        "TV2 Sport X Dansk HD",
        "Ziggo Sport 2",
        "Italian W/Serie A - Week 12"
      ]
    },
    {
      "competition": "Dutch Eredivisie - Week 21",
      "title": "Juventus v Sassuolo",
      "kickoff_baghdad": "11:00",
      "channels_raw": [
        "DAZN Italia ($/geo/R)",
        "W-Sport HD",
        "Spanish Liga F Femenino - Week 18"
      ]
    },
    {
      "competition": "Dutch Eredivisie - Week 21",
      "title": "Badalona v Eibar",
      "kickoff_baghdad": "11:00",
      "channels_raw": [
        "DAZN España ($/geo/R)",
        "Türkiye Süper Lig - Week 20"
      ]
    },
    {
      "competition": "Dutch Eredivisie - Week 21",
      "title": "Galatasaray v Kayserispor",
      "kickoff_baghdad": "11:00",
      "channels_raw": [
        "Arena Sport 2 Srbija HD",
        "beIN Connect Australia",
        "beIN Connect Canada",
        "beIN Connect Hong Kong",
        "beIN Connect Indonesia",
        "beIN Connect Malaysia",
        "beIN Connect New Zealand",
        "beIN Connect Philippines",
        "beIN Connect Singapore",
        "beIN Connect Thailand",
        "beIN Connect Türkiye",
        "beIN Connect USA",
        "beIN Sports France 3 HD",
        "beIN Sports Indonesia 2 HD",
        "beIN Sports Philippines 2 HD",
        "beIN Sports Singapore HD",
        "beIN Sports Thailand 2 HD",
        "beIN Sports Türkiye 1 HD",
        "beIN Sports US 5",
        "MATCH! Futbol 3 HD",
        "Sport 2 Hungary HD",
        "Sport TV5 Portugal HD",
        "SportKlub 2 Hrvatska",
        "SportKlub 2 Slovenija",
        "Belgian Pro League - Week 23"
      ]
    },
    {
      "competition": "Dutch Eredivisie - Week 21",
      "title": "Union St Gilloise v Club Brugge",
      "kickoff_baghdad": "11:30",
      "channels_raw": [
        "DAZN Belgium ($/geo/R)",
        "DAZN Great Britain (geo/R)",
        "DAZN Ireland ($/geo/R)",
        "DAZN Pro League 1 HD",
        "German Frauen Bundesliga - Week 16"
      ]
    },
    {
      "competition": "Dutch Eredivisie - Week 21",
      "title": "RB Leipzig v Eintracht Frankfurt",
      "kickoff_baghdad": "11:30",
      "channels_raw": [
        "DAZN Deutsch ($/geo/R)",
        "Magenta Sport ($/geo/R)",
        "Greek Super League 1 - Week 19"
      ]
    },
    {
      "competition": "Dutch Eredivisie - Week 21",
      "title": "PAOK Thessaloniki v Panserraikos",
      "kickoff_baghdad": "11:30",
      "channels_raw": [
        "Nova Sports Prime Cyprus HD",
        "Nova Sports Prime Hellas HD",
        "Italian Serie C Girone B - Girone B - 24"
      ]
    },
    {
      "competition": "Dutch Eredivisie - Week 21",
      "title": "Forli v Rimini",
      "kickoff_baghdad": "11:30",
      "channels_raw": [
        "** C-A-N-C-E-L-L-E-D **",
        "Saudi Pro League - Week 20"
      ]
    },
    {
      "competition": "Dutch Eredivisie - Week 21",
      "title": "Al Ittihad v Al Najma",
      "kickoff_baghdad": "11:30",
      "channels_raw": [
        "S Sport+ Streaming",
        "Setanta Sports Premium HD",
        "Sport TV7 Portugal HD",
        "Thmanyah KSA [app]",
        "Saudi Pro League - Week 20"
      ]
    },
    {
      "competition": "Dutch Eredivisie - Week 21",
      "title": "Al Fateh v Al Hazem",
      "kickoff_baghdad": "11:30",
      "channels_raw": [
        "Thmanyah KSA [app]",
        "Spanish La Liga (Primera) - Week 22"
      ]
    },
    {
      "competition": "Dutch Eredivisie - Week 21",
      "title": "Getafe v Celta Vigo",
      "kickoff_baghdad": "12:00",
      "channels_raw": [
        "beIN Connect MENA",
        "beIN Sports Australia 2 HD",
        "beIN Sports MENA 5 HD",
        "beIN Sports MENA French 1 HD",
        "DAZN 2 Portugal HD",
        "DAZN Belgium ($/geo/R)",
        "DAZN Deutsch ($/geo/R)",
        "DAZN Italia ($/geo/R)",
        "DAZN USA en Español ($/geo/R)",
        "ESPN Deportes",
        "ESPN+ USA ($/geo/R)",
        "Fast Sports [online] ($/geo/R)",
        "Fubo Sports USA ($/geo/R)",
        "LaLiga TV Bar HD",
        "MTV Katsomon+ ($/geo/R)",
        "ONE Sport Israel HD",
        "Premier Sports 1 Ireland HD",
        "Premier Sports 1 UK HD",
        "Premier Sports GB Player HD",
        "S Sport 1 Türkiye HD",
        "S Sport+ Streaming",
        "TSN+ Canada ($/geo/R)",
        "TV2 Play Danmark ($/geo/R)",
        "TV2 Play Norge ($/geo/R)",
        "TV4 Play Sverige [online]",
        "ViaPlay Norge HD",
        "Ziggo Sport HD",
        "FIFA Womens Champions Cup - FINAL",
        "** T.B.D. **",
        "Sky Go UK [online]",
        "Sky Sports Football HD",
        "Israeli Ligat ha'Al (Premier) - Week 21"
      ]
    },
    {
      "competition": "Dutch Eredivisie - Week 21",
      "title": "Hapoel Petah Tikva v Ashdod",
      "kickoff_baghdad": "12:00",
      "channels_raw": [
        "5 LIVE Israel HD",
        "Portuguese Liga Portugal - Week 20"
      ]
    },
    {
      "competition": "Dutch Eredivisie - Week 21",
      "title": "Sporting Lisbon v Nacional Madeira",
      "kickoff_baghdad": "12:00",
      "channels_raw": [
        "Arena Sport 1 Slovakia HD",
        "beIN Sports France 4 HD max",
        "Megogo Sport Kazakhstan [$]",
        "Sport 2 Israel HD",
        "Sport TV+ Portugal",
        "Romanian Superliga - Week 24"
      ]
    },
    {
      "competition": "Dutch Eredivisie - Week 21",
      "title": "FCSB v Csikszereda",
      "kickoff_baghdad": "12:00",
      "channels_raw": [
        "Digi Sport 1 Romania HD",
        "Prima Sport RO 1 HD",
        "Belgian Pro League - Week 23"
      ]
    },
    {
      "competition": "Dutch Eredivisie - Week 21",
      "title": "Leuven v Mechelen",
      "kickoff_baghdad": "12:15",
      "channels_raw": [
        "DAZN Belgium ($/geo/R)",
        "DAZN Pro League 2 HD",
        "German 3. Liga - Week 22"
      ]
    },
    {
      "competition": "Dutch Eredivisie - Week 21",
      "title": "Rot-Weiss Essen v Wehen Wiesbaden",
      "kickoff_baghdad": "12:30",
      "channels_raw": [
        "Magenta Sport ($/geo/R)",
        "OneFootball [app] ($/geo/R)",
        "Colombian Primera A - Week 4"
      ]
    },
    {
      "competition": "Dutch Eredivisie - Week 21",
      "title": "Bucaramanga v Petrolera",
      "kickoff_baghdad": "13:00",
      "channels_raw": [
        "Fanatiz USA ($/geo/R)",
        "Dutch Eredivisie - Week 21"
      ]
    },
    {
      "competition": "Dutch Eredivisie - Week 21",
      "title": "Volendam v Go Ahead Eagles",
      "kickoff_baghdad": "13:00",
      "channels_raw": [
        "ESPN 1 Nederland HD",
        "ESPN Extra Nederland",
        "Greek Super League 1 - Week 19"
      ]
    },
    {
      "competition": "Dutch Eredivisie - Week 21",
      "title": "AEK Athens v Olympiacos",
      "kickoff_baghdad": "13:00",
      "channels_raw": [
        "Cosmote Sport 1 HD",
        "Cytavision Sports 3 HD",
        "French Ligue 1 - Week 20"
      ]
    },
    {
      "competition": "Dutch Eredivisie - Week 21",
      "title": "Strasbourg v Paris St Germain",
      "kickoff_baghdad": "13:45",
      "channels_raw": [
        "beIN Connect MENA",
        "beIN Connect Türkiye",
        "beIN Connect USA",
        "beIN Sports MENA 1 HD",
        "beIN Sports MENA French 1 HD",
        "beIN Sports Türkiye 4 HD",
        "DAZN France ($/geo/R)",
        "Fanatiz USA ($/geo/R)",
        "Fubo Sports USA ($/geo/R)",
        "Ligue 1+ ($/geo/R)",
        "Prime Video UK PPV [$]",
        "Sport TV Azerbaijan (geo/R)",
        "SuperSport Variety 4 HD",
        "TV3 Sport Dansk HD",
        "Varzish TV Sport HD (tjk)",
        "ViaPlay Danmark HD",
        "ViaPlay Nederland HD",
        "ViaPlay Norge HD",
        "ViaPlay Suomi HD",
        "ViaPlay Sverige HD",
        "Italian Serie A - Week 23"
      ]
    },
    {
      "competition": "Dutch Eredivisie - Week 21",
      "title": "Parma v Juventus",
      "kickoff_baghdad": "13:45",
      "channels_raw": [
        "beIN Sports Australia 3 HD",
        "Cosmote Sport 2 HD",
        "DAZN Belgium ($/geo/R)",
        "DAZN Great Britain (geo/R)",
        "DAZN Ireland ($/geo/R)",
        "DAZN Italia ($/geo/R)",
        "DAZN USA en Español ($/geo/R)",
        "Paramount+ USA ($/geo/R)",
        "S Sport 2 Türkiye HD",
        "S Sport+ Streaming",
        "Sport 1 Israel HD",
        "Sport TV 2 Azerbaijan (geo/R)",
        "Tivibu Spor 1 HD",
        "Tring Sport 1 HD",
        "Ziggo Sport 2",
        "Spanish La Liga (Primera) - Week 22"
      ]
    },
    {
      "competition": "Dutch Eredivisie - Week 21",
      "title": "Athletic Bilbao v Real Sociedad",
      "kickoff_baghdad": "14:00",
      "channels_raw": [
        "beIN Connect MENA",
        "beIN Sports Australia 2 HD",
        "beIN Sports France 1 HD",
        "beIN Sports MENA 5 HD",
        "beIN Sports MENA English 1 HD",
        "beIN Sports MENA French 1 HD",
        "DAZN 1 Portugal HD",
        "DAZN Belgium ($/geo/R)",
        "DAZN Deutsch ($/geo/R)",
        "DAZN España ($/geo/R)",
        "DAZN Italia ($/geo/R)",
        "DAZN LaLiga HD",
        "DAZN USA en Español ($/geo/R)",
        "ESPN Deportes",
        "ESPN+ USA ($/geo/R)",
        "Fast Sports [online] ($/geo/R)",
        "Fubo Sports USA ($/geo/R)",
        "Futbol TV Tajikistan",
        "Idman TV HD",
        "LaLiga TV Bar HD",
        "M+ LaLiga HD",
        "M+ LaLiga HDR",
        "MTV Katsomon+ ($/geo/R)",
        "ONE Sport Israel HD",
        "Premier Sports 1 Ireland HD",
        "Premier Sports 1 UK HD",
        "Premier Sports GB Player HD",
        "S Sport 1 Türkiye HD",
        "S Sport+ Streaming",
        "TSN+ Canada ($/geo/R)",
        "TV2 Play Danmark ($/geo/R)",
        "TV2 Play Norge ($/geo/R)",
        "TV2 Sport X Dansk HD",
        "TV4 Play Sverige [online]",
        "ViaPlay Norge HD",
        "Ziggo Sport HD",
        "Spanish La Liga 2 - Week 24"
      ]
    },
    {
      "competition": "Dutch Eredivisie - Week 21",
      "title": "Granada v Racing Santander",
      "kickoff_baghdad": "14:00",
      "channels_raw": [
        "beIN Sports France 5 HD max",
        "Portuguese Liga Portugal - Week 20"
      ]
    },
    {
      "competition": "Dutch Eredivisie - Week 21",
      "title": "Tondela v Benfica",
      "kickoff_baghdad": "14:30",
      "channels_raw": [
        "Arena Sport 1 Slovakia HD",
        "S Sport+ Streaming",
        "Sport 2 Israel HD",
        "Sport TV1 Portugal HD",
        "Tivibu Spor 2 HD",
        "Colombian Primera A - Week 4"
      ]
    },
    {
      "competition": "Dutch Eredivisie - Week 21",
      "title": "Deportivo Cali v Deportivo Pasto",
      "kickoff_baghdad": "15:10",
      "channels_raw": [
        "Fanatiz USA ($/geo/R)",
        "Argentinean Primera División - Week 3"
      ]
    },
    {
      "competition": "Dutch Eredivisie - Week 21",
      "title": "Boca Juniors v Newell's Old Boys",
      "kickoff_baghdad": "16:15",
      "channels_raw": [
        "Dubai Sports 1 HD",
        "Premier Sports 1 Ireland HD",
        "Premier Sports 1 UK HD",
        "Premier Sports 2 UK HD",
        "Premier Sports GB Player HD",
        "Sport 3 Israel HD",
        "Sportdigital FUSSBALL HD",
        "Colombian Primera A - Week 4"
      ]
    },
    {
      "competition": "Dutch Eredivisie - Week 21",
      "title": "Once Caldas v Jaguares Córdoba",
      "kickoff_baghdad": "17:10",
      "channels_raw": [
        "Fanatiz USA ($/geo/R)",
        "Argentinean Primera División - Week 3"
      ]
    },
    {
      "competition": "Dutch Eredivisie - Week 21",
      "title": "Rosario Central v River Plate",
      "kickoff_baghdad": "18:30",
      "channels_raw": [
        "Dubai Sports 1 HD",
        "Premier Sports GB Player HD",
        "Sport 3 Israel HD",
        "Colombian Primera A - Week 4"
      ]
    },
    {
      "competition": "Dutch Eredivisie - Week 21",
      "title": "Millonarios v Independiente Medellín",
      "kickoff_baghdad": "19:10",
      "channels_raw": [
        "Fanatiz USA ($/geo/R)",
        "Colombian Primera A - Week 4"
      ]
    },
    {
      "competition": "Dutch Eredivisie - Week 21",
      "title": "Llaneros v Rionegro Águilas",
      "kickoff_baghdad": "19:30",
      "channels_raw": [
        "Fanatiz USA ($/geo/R)",
        "L.J.'s LIVE Football on Satellite TV. LiveOnSat.com. LJ-Sport.com. All Rights",
        "Reserved. Copyright (c) 1997 - 2026",
        "Cookie Consent by",
        "Free Privacy Policy Generator website"
      ]
    }
  ]
}