{
  "date": "2026-02-04",
  "source_url": "https://m.liveonsat.com/2day.php",
  "matches": [
    {
      "competition": "Türkiye Cup - Group Stage: Round 3",
      "title": "Boluspor v Alanyaspor",
      "kickoff_baghdad": "02:00",
      "channels_raw": [
        "A Spor Türkiye HD",
        "Discover more",
        "Spor",
        "Sports",
        "Sports streaming services",
        "Sports memorabilia",
        "Fan apparel",
        "Training equipment",
        "La Liga Subscription",
        "Football jerseys",
        "Europa League Tickets",
        "Ligue 1 Jerseys",
        "Türkiye Cup - Group Stage: Round 3"
      ]
    },
    {
      "competition": "Türkiye Cup - Group Stage: Round 3",
      "title": "Fatih Karagümrük v Istanbul Basaksehir",
      "kickoff_baghdad": "04:30",
      "channels_raw": [
        "A Spor Türkiye HD",
        "SportKlub 1 Hrvatska HD",
        "SportKlub 1 Slovenija HD",
        "UEFA Youth League (U-19) - Round of 32"
      ]
    },
    {
      "competition": "Türkiye Cup - Group Stage: Round 3",
      "title": "Legia Warsaw U-19 v Ajax U-19",
      "kickoff_baghdad": "05:00",
      "channels_raw": [
        "SuperSport Football HD",
        "SuperSport MáXimo 1 HD",
        "SuperSport MáXimo 360",
        "UEFA.TV [online] (geo/R)",
        "Romanian Superliga - Week 25"
      ]
    },
    {
      "competition": "Türkiye Cup - Group Stage: Round 3",
      "title": "Metaloglobus v Csikszereda",
      "kickoff_baghdad": "06:00",
      "channels_raw": [
        "Digi Sport 1 Romania HD",
        "Prima Sport RO 1 HD",
        "Qatar Stars League - Week 15"
      ]
    },
    {
      "competition": "Türkiye Cup - Group Stage: Round 3",
      "title": "Umm Salal v Al Duhail",
      "kickoff_baghdad": "06:45",
      "channels_raw": [
        "beIN Sports MENA Global HD",
        "Türkiye Cup - Group Stage: Round 3"
      ]
    },
    {
      "competition": "Türkiye Cup - Group Stage: Round 3",
      "title": "Gençlerbirligi v Eyüpspor",
      "kickoff_baghdad": "07:00",
      "channels_raw": [
        "A Spor Türkiye HD",
        "SportKlub 1 Hrvatska HD",
        "SportKlub 1 Slovenija HD",
        "UEFA Youth League (U-19) - Round of 32"
      ]
    },
    {
      "competition": "Türkiye Cup - Group Stage: Round 3",
      "title": "HJK Helsinki U-19 v Manchester City U-19",
      "kickoff_baghdad": "07:00",
      "channels_raw": [
        "beIN Sports MENA English 1 HD",
        "City+ ($/geo/R)",
        "Discovery+ UK ($/geo/R)",
        "SuperSport Football HD",
        "SuperSport MáXimo 1 HD",
        "SuperSport MáXimo 360",
        "TNT Sports 4 HD",
        "TNT Sports 5 HD",
        "TNT Sports 6",
        "TV3 Sport Dansk HD",
        "UEFA.TV [online] (geo/R)",
        "Discover more",
        "Spor",
        "Live Video Streaming",
        "Movie & TV Streaming",
        "Sport",
        "Sports News",
        "Soccer",
        "Sporting",
        "TV & Video",
        "Sports",
        "TV Networks & Stations",
        "UEFA Youth League (U-19) - Round of 32"
      ]
    },
    {
      "competition": "Türkiye Cup - Group Stage: Round 3",
      "title": "Benfica U-19 v Slavia Prague U-19",
      "kickoff_baghdad": "07:00",
      "channels_raw": [
        "Nova Sport 4 Czech HD",
        "Romanian Superliga - Week 25"
      ]
    },
    {
      "competition": "Türkiye Cup - Group Stage: Round 3",
      "title": "UTA Arad v CFR Cluj",
      "kickoff_baghdad": "08:00",
      "channels_raw": [
        "Digi Sport 1 Romania HD",
        "Prima Sport RO 1 HD",
        "UEFA Youth League (U-19) - Round of 32"
      ]
    },
    {
      "competition": "Türkiye Cup - Group Stage: Round 3",
      "title": "Maccabi Haifa U-19 v Barcelona U-19",
      "kickoff_baghdad": "08:00",
      "channels_raw": [
        "5 PLUS Israel HD",
        "Greek Super League 1 - Week 17"
      ]
    },
    {
      "competition": "Türkiye Cup - Group Stage: Round 3",
      "title": "Asteras Tripolis v Olympiacos",
      "kickoff_baghdad": "08:30",
      "channels_raw": [
        "Nova Sports 2 Cyprus HD",
        "Nova Sports 2 Hellas HD",
        "Telekanal Futbol HD",
        "Discover more",
        "FIFA+ Stream Live Football TV",
        "Football jerseys",
        "Football boots",
        "TV",
        "La Liga Subscription",
        "Team merchandise",
        "FIFA video games",
        "Spor",
        "Activewear",
        "Soccer balls",
        "Cypriot 1. Division - Week 15"
      ]
    },
    {
      "competition": "Türkiye Cup - Group Stage: Round 3",
      "title": "Pafos FC v APOEL Nicosia",
      "kickoff_baghdad": "09:00",
      "channels_raw": [
        "Cablenet Sports 1 HD",
        "Cosmote Sport 3 HD",
        "German Frauen Bundesliga - Week 15"
      ]
    },
    {
      "competition": "Türkiye Cup - Group Stage: Round 3",
      "title": "Eintracht Frankfurt v Hoffenheim",
      "kickoff_baghdad": "09:00",
      "channels_raw": [
        "DAZN 2 Bar Deutsch HD",
        "DAZN Belgium ($/geo/R)",
        "DAZN Deutsch ($/geo/R)",
        "DAZN Great Britain (geo/R)",
        "DAZN Ireland ($/geo/R)",
        "DAZN Italia ($/geo/R)",
        "Magenta Sport ($/geo/R)",
        "UEFA Youth League (U-19) - Round of 32"
      ]
    },
    {
      "competition": "Türkiye Cup - Group Stage: Round 3",
      "title": "Real Betis U-19 v Tottenham U-19",
      "kickoff_baghdad": "09:00",
      "channels_raw": [
        "beIN Sports MENA 2 HD",
        "Cytavision Sports 6 HD",
        "Discovery+ UK ($/geo/R)",
        "SuperSport Football HD",
        "SuperSport MáXimo 360",
        "TNT Sports 4 HD",
        "TV3 Sport Dansk HD",
        "UEFA.TV [online] (geo/R)",
        "UEFA Youth League (U-19) - Round of 32"
      ]
    },
    {
      "competition": "Türkiye Cup - Group Stage: Round 3",
      "title": "FC Cologne U-19 v Inter Milan U-19",
      "kickoff_baghdad": "09:00",
      "channels_raw": [
        "Cytavision Sports 4 HD",
        "DAZN 1 Bar Deutsch HD",
        "SuperSport MáXimo 1 HD",
        "UEFA.TV [online] (geo/R)",
        "Türkiye Cup - Group Stage: Round 3"
      ]
    },
    {
      "competition": "Türkiye Cup - Group Stage: Round 3",
      "title": "Galatasaray v Istanbulspor",
      "kickoff_baghdad": "09:30",
      "channels_raw": [
        "A Spor Türkiye HD",
        "MAX Sport 4 Bulgaria HD",
        "Persiana Sports 2 HD",
        "SportKlub 1 Hrvatska HD",
        "SportKlub 1 Slovenija HD",
        "VG+ Sport Norge ($/geo/R)",
        "Romanian Superliga - Week 25"
      ]
    },
    {
      "competition": "Türkiye Cup - Group Stage: Round 3",
      "title": "Farul Constanta v Dinamo Bucharest",
      "kickoff_baghdad": "10:30",
      "channels_raw": [
        "Digi Sport 1 Romania HD",
        "Prima Sport RO 1 HD",
        "Belgian Cup (Beker van België) - Semi Final (1st Leg)"
      ]
    },
    {
      "competition": "Türkiye Cup - Group Stage: Round 3",
      "title": "Sporting Charleroi v Union St Gilloise",
      "kickoff_baghdad": "11:00",
      "channels_raw": [
        "DAZN Great Britain (geo/R)",
        "DAZN Ireland ($/geo/R)",
        "DAZN Pro League 1 HD",
        "Discover more",
        "Sports streaming services",
        "Television",
        "Europa League Tickets",
        "TV Schedule App",
        "FIFA+ Stream Live Football TV",
        "Ice Hockey Jerseys",
        "La Liga Subscription",
        "Collectible trading cards",
        "Ligue 1 Jerseys",
        "Womens Football Gear",
        "Belgian Cup (Beker van België) - Semi Final (1st Leg)"
      ]
    },
    {
      "competition": "Türkiye Cup - Group Stage: Round 3",
      "title": "Anderlecht v Antwerp",
      "kickoff_baghdad": "11:00",
      "channels_raw": [
        "DAZN Great Britain (geo/R)",
        "DAZN Ireland ($/geo/R)",
        "DAZN Pro League 1 HD",
        "Swiss Cup (Schweizer Pokal) - Quarter Final"
      ]
    },
    {
      "competition": "Türkiye Cup - Group Stage: Round 3",
      "title": "St Gallen v Basel",
      "kickoff_baghdad": "11:15",
      "channels_raw": [
        "Play RTS Sport (geo/R)",
        "RSI La 2 Svizzera HD",
        "RTS 2 Suisse HD",
        "SRF Zwei Schweiz HD",
        "French Cup (Coupe de France) - 5th Round"
      ]
    },
    {
      "competition": "Türkiye Cup - Group Stage: Round 3",
      "title": "Lorient v Paris FC",
      "kickoff_baghdad": "11:30",
      "channels_raw": [
        "beIN Sports France 6 HD max",
        "beIN Sports MENA 2 HD",
        "beIN Sports Türkiye 5 HD",
        "Cytavision Sports 7 HD",
        "Nova Sport 5 Czech HD",
        "Sport TV1 Slovenija",
        "Sport TV5 Portugal HD",
        "VG+ Sport Norge ($/geo/R)",
        "French Cup (Coupe de France) - 5th Round"
      ]
    },
    {
      "competition": "Türkiye Cup - Group Stage: Round 3",
      "title": "Toulouse v Amiens",
      "kickoff_baghdad": "11:30",
      "channels_raw": [
        "beIN Sports France 4 HD max",
        "beIN Sports MENA 5 HD",
        "beIN Sports Türkiye Max 2 HD",
        "Prima Sport RO PPV 4",
        "VG+ Sport Norge ($/geo/R)",
        "French Cup (Coupe de France) - 5th Round"
      ]
    },
    {
      "competition": "Türkiye Cup - Group Stage: Round 3",
      "title": "Nice v Montpellier",
      "kickoff_baghdad": "11:30",
      "channels_raw": [
        "beIN Sports France 5 HD max",
        "beIN Sports MENA 3 HD",
        "beIN Sports Türkiye Max 1 HD",
        "Silk Universal HD",
        "Sport TV3 Slovenija",
        "VG+ Sport Norge ($/geo/R)",
        "French Cup (Coupe de France) - 5th Round"
      ]
    },
    {
      "competition": "Türkiye Cup - Group Stage: Round 3",
      "title": "Lyon v Laval",
      "kickoff_baghdad": "11:30",
      "channels_raw": [
        "beIN Sports France 3 HD",
        "beIN Sports MENA 6 HD",
        "beIN Sports Türkiye 3 HD",
        "Fox Soccer Plus USA",
        "MAX Sport 1 Bulgaria HD",
        "Nova Sport 4 Czech HD",
        "Prima Sport RO PPV 2",
        "Sport TV6 Portugal HD",
        "VG+ Sport Norge ($/geo/R)",
        "Polish Ekstraklasa - Week 16"
      ]
    },
    {
      "competition": "Türkiye Cup - Group Stage: Round 3",
      "title": "Jagiellonia v GKS Katowice",
      "kickoff_baghdad": "11:30",
      "channels_raw": [
        "Canal+ Sport 3 Polska HD",
        "Ekstraklasa TV ($/PPV)",
        "German Cup (DFB-Pokal) - Quarter Final"
      ]
    },
    {
      "competition": "Türkiye Cup - Group Stage: Round 3",
      "title": "Holstein Kiel v Stuttgart",
      "kickoff_baghdad": "11:45",
      "channels_raw": [
        "Abu Dhabi Sports 2 HD",
        "Arena Sport 1 BiH HD",
        "Arena Sport 2 Hrvatska HD",
        "Arena Sport 2 Srbija HD",
        "Arena Sport 3 Slovenija HD",
        "ART Motion Sport 4 HD",
        "Azam Sports 2 HD",
        "beIN Sports France 9 HD max",
        "DAZN 1 Portugal HD",
        "DFB Play TV (geo/R)",
        "Diema Sport 3 HD",
        "Digi Sport 3 Romania",
        "Eleven Sports 2 Polska HD",
        "Go3 Sport Open Baltic",
        "GOL España HD",
        "La Chaine L´Équipe HD",
        "Nova Sport 3 Czech HD",
        "QazSport HD",
        "Sifir Tv",
        "Sky Sport MIX Deutsch HD",
        "Sky Sport News Deutsch HD",
        "Sky Sport Top Event HD",
        "Sport 2 Hungary HD",
        "Sport 3 Israel HD",
        "SuperSport 4 Albania HD",
        "SuperSport ESPN HD",
        "VG+ Sport Norge ($/geo/R)",
        "ZDF Deutschland HD",
        "Ziggo Sport 3",
        "Scottish Premiership - Week 25"
      ]
    },
    {
      "competition": "Türkiye Cup - Group Stage: Round 3",
      "title": "Rangers v Kilmarnock",
      "kickoff_baghdad": "11:45",
      "channels_raw": [
        "Kilmarnock TV ($/geo/R)",
        "Rangers TV ($/geo/R)",
        "Scottish Premiership - Week 25"
      ]
    },
    {
      "competition": "Türkiye Cup - Group Stage: Round 3",
      "title": "Hibernian v Dundee United",
      "kickoff_baghdad": "11:45",
      "channels_raw": [
        "Dundee United TV [$]",
        "Hibs TV ($/geo/R)",
        "Scottish Premiership - Week 25"
      ]
    },
    {
      "competition": "Türkiye Cup - Group Stage: Round 3",
      "title": "Dundee v Motherwell",
      "kickoff_baghdad": "11:45",
      "channels_raw": [
        "Dundee TV ($/geo/R)",
        "Motherwell TV ($/geo/R)",
        "Scottish Premiership - Week 25"
      ]
    },
    {
      "competition": "Türkiye Cup - Group Stage: Round 3",
      "title": "Livingston v Falkirk",
      "kickoff_baghdad": "11:45",
      "channels_raw": [
        "Falkirk TV [$]",
        "Dutch Cup (KNVB Beker)"
      ]
    },
    {
      "competition": "Türkiye Cup - Group Stage: Round 3",
      "title": "PSV Eindhoven v Heerenveen",
      "kickoff_baghdad": "12:00",
      "channels_raw": [
        "Arena Sport 1 Slovakia HD",
        "Cablenet Sports 2 HD",
        "Play Sports 3 Belgium",
        "Ring Bulgaria HD",
        "Sportdigital FUSSBALL HD",
        "SuperSport 5 Albania HD",
        "English League Cup - Semi Final (2nd Leg) [2-0]"
      ]
    },
    {
      "competition": "Türkiye Cup - Group Stage: Round 3",
      "title": "Manchester City v Newcastle United",
      "kickoff_baghdad": "12:00",
      "channels_raw": [
        "Action 24 Hellas",
        "Arena Premium 1 BiH HD",
        "Arena Premium 1 Srbija HD",
        "Arena Sport 1 Hrvatska HD",
        "Arena Sport 1 Slovenija HD",
        "Azam Sports 1 HD",
        "beIN Sports France 7 HD max",
        "beIN Sports MENA 1 HD",
        "beIN Sports MENA English 1 HD",
        "Canal+ Sport 3 Afrique HD",
        "DAZN Canada ($/geo/R)",
        "DAZN Japan ($/geo/R)",
        "Diema Sport 2 HD",
        "Digi Sport 2 Romania HD",
        "ESPN 1 Brazil HD",
        "EXXEN Digital Türkiye [$]",
        "Fast Sports TV Armenia",
        "IRIB TV3 HD",
        "Match 4 Hungary HD",
        "Nova Sport 2 Czech HD",
        "Persiana Sport HD",
        "Setanta Sports 1 Baltic",
        "Setanta Sports 1 Eurasia HD",
        "Setanta Sports Ukraine HD",
        "Sky Go UK [online]",
        "Sky Sport Premier League DE HD",
        "Sky Sports Football HD",
        "Sky Sports Main Event HD",
        "Sky Sports Main Event UHD",
        "Sky UK Ultra HD 1",
        "Sport 2 Israel HD",
        "Sport TV1 Portugal HD",
        "Sporty TV Africa",
        "ST World Football HD",
        "SuperSport 2 Albania HD",
        "SuperSport MáXimo 1 HD",
        "SuperSport MáXimo 2A HD",
        "SuperSport Premier League HD",
        "TV3 MAX Dansk HD"
      ]
    },
    {
      "competition": "Türkiye Cup - Group Stage: Round 3",
      "title": "V Sport 1 Norge HD",
      "kickoff_baghdad": null,
      "channels_raw": [
        "Varzish TV Sport HD (tjk)",
        "ViaPlay 2 Urheilu HD",
        "ViaPlay Danmark HD",
        "ViaPlay Nederland HD",
        "ViaPlay Norge HD",
        "ViaPlay Sport Sverige HD",
        "ViaPlay Suomi HD",
        "ViaPlay Sverige HD",
        "ViaPlay Ísland HD",
        "Italian Cup (Coppa Italia) - Quarter Final"
      ]
    },
    {
      "competition": "Türkiye Cup - Group Stage: Round 3",
      "title": "Inter Milan v Torino",
      "kickoff_baghdad": "12:00",
      "channels_raw": [
        "Arena 4 Hungary HD",
        "Arena Premium 1 Slovenija",
        "Arena Premium 2 BiH HD",
        "Arena Premium 2 Srbija HD",
        "Arena Sport 4 Hrvatska HD",
        "ART Motion Sport 1 HD",
        "Azam Sports 3 HD",
        "Bold+ Dansk ($/geo/R)",
        "CBS Sports Golazo N/W (geo/R)",
        "Cytavision Sports 4 HD",
        "DAZN 1 Bar Deutsch HD",
        "DAZN 1 Bar Espana",
        "DAZN 1 Espana HD",
        "DAZN France ($/geo/R)",
        "Italia 1 HD",
        "MATCH! Russia HD",
        "MAX Sport 3 Bulgaria HD",
        "Nova Sports 1 Hellas HD",
        "Persiana Sports 2 HD",
        "Polsat Sport Premium 1 HD",
        "Premier Sports 1 Ireland HD",
        "Premier Sports 1 UK HD",
        "Premier Sports GB Player HD",
        "Sport 1 Czechia HD",
        "Sport 4 Israel HD",
        "Sport Bladet Play (geo/R)",
        "Sport Live Dansk HD",
        "Sport TV4 Portugal HD",
        "Sport+ Qazaqstan",
        "Tring Sport 1 HD",
        "TRT Spor Türkiye HD",
        "VG+ Sport Norge ($/geo/R)",
        "Ziggo Sport HD",
        "Scottish Premiership - Week 25"
      ]
    },
    {
      "competition": "Türkiye Cup - Group Stage: Round 3",
      "title": "Aberdeen v Celtic",
      "kickoff_baghdad": "12:00",
      "channels_raw": [
        "Arena Sport 1 Srbija HD",
        "Arena Sport 5 BiH HD",
        "ART Motion Sport 2 HD",
        "Celtic TV ($/geo/R)",
        "Cosmote Sport 3 HD",
        "Paramount+ USA ($/geo/R)",
        "Polsat Sport Extra 1 HD",
        "Red TV ($/geo/R)",
        "S Sport+ Streaming",
        "Setanta Sports 2 Eurasia HD",
        "Setanta Sports 2 Georgia HD#0",
        "Setanta Sports+ Ukraine HD",
        "Sharjah Sports HD",
        "Sky Go UK [online]",
        "Sky Sports Football HD",
        "Sky Sports Main Event HD",
        "Sky Sports Main Event UHD",
        "Sky UK Ultra HD 1",
        "Sport TV7 Portugal HD",
        "Sportdigital 1+ Deutsch HD",
        "SuperSport 1 Albania HD",
        "Tabii Spor Türkiye ($/geo/R)",
        "Spanish Cup (Copa del Rey) - Quarter Final"
      ]
    },
    {
      "competition": "Türkiye Cup - Group Stage: Round 3",
      "title": "Valencia v Athletic Bilbao",
      "kickoff_baghdad": "12:00",
      "channels_raw": [
        "Arena Premium 3 BiH HD",
        "Arena Premium 4 Srbija HD",
        "Arena Sport 2 Slovenija HD",
        "Arena Sport 3 Hrvatska HD",
        "Cytavision Sports 6 HD",
        "DAZN 2 Bar Deutsch HD",
        "DAZN France ($/geo/R)",
        "Digi Sport 4 Romania",
        "Eleven Sports 1 Polska HD",
        "LaLiga TV Bar HD",
        "M+ LaLiga HD",
        "MATCH! Futbol 2 HD",
        "MAX Sport 4 Bulgaria HD",
        "Prima Sport RO 2 HD",
        "Sport 1 Hungary HD",
        "Sport 1 Israel HD",
        "Sport TV3 Portugal HD",
        "ST Sports Premium HD",
        "SuperSport 3 Albania HD",
        "Ziggo Sport 2",
        "Zor TV Uzbekistan",
        "Spanish Cup (Copa del Rey) - Quarter Final"
      ]
    },
    {
      "competition": "Türkiye Cup - Group Stage: Round 3",
      "title": "Alavés v Real Sociedad",
      "kickoff_baghdad": "12:00",
      "channels_raw": [
        "Arena Premium 5 Srbija HD",
        "Arena Sport 3 BiH HD",
        "Arena Sport 4 Slovenija HD",
        "Arena Sport 6 Hrvatska HD",
        "Cytavision Sports 5 HD",
        "DAZN France ($/geo/R)",
        "Eleven Sports 3 Polska HD",
        "ESPN 4 Brazil HD",
        "Futbol TV Tajikistan",
        "LaLiga TV Bar 2",
        "M+ LaLiga 2 HD",
        "MATCH! Futbol 1 HD",
        "Prima Sport RO 3 HD",
        "Prima Sport RO 5 HD",
        "ST Sports Life",
        "French Cup (Coupe de France) - 5th Round"
      ]
    },
    {
      "competition": "Türkiye Cup - Group Stage: Round 3",
      "title": "Troyes v Lens",
      "kickoff_baghdad": "12:05",
      "channels_raw": [
        "beIN Sports France 1 HD",
        "beIN Sports MENA 8 HD",
        "beIN Sports MENA French 1 HD",
        "beIN Sports Türkiye 4 HD",
        "Cytavision Sports 8 HD",
        "ERT 2 Sport Hellas HD",
        "Fox Sports 2 USA HD",
        "Nova Sport 6 Czech HD",
        "Prima Sport RO PPV 3",
        "Sport TV2 Slovenija",
        "Brazilian Série A - Week 2"
      ]
    },
    {
      "competition": "Türkiye Cup - Group Stage: Round 3",
      "title": "Bragantino v Atlético Mineiro",
      "kickoff_baghdad": "14:00",
      "channels_raw": [
        "Arena Premium 2 Srbija HD",
        "Arena Sport 1 BiH HD",
        "Spor Smart Türkiye HD",
        "Brazilian Série A - Week 2"
      ]
    },
    {
      "competition": "Türkiye Cup - Group Stage: Round 3",
      "title": "Santos v São Paulo",
      "kickoff_baghdad": "15:00",
      "channels_raw": [
        "Premier Sports 1 Ireland HD",
        "Premier Sports 1 UK HD",
        "Premier Sports 2 Ireland HD",
        "Premier Sports 2 UK HD",
        "Premier Sports GB Player HD",
        "Spor Smart 2 Türkiye HD",
        "Sport 4 Israel HD",
        "Brazilian Série A - Week 2"
      ]
    },
    {
      "competition": "Türkiye Cup - Group Stage: Round 3",
      "title": "Palmeiras v Vitória Bahia",
      "kickoff_baghdad": "16:30",
      "channels_raw": [
        "Spor Smart Türkiye HD",
        "Thursday, 5th February",
        "Türkiye Cup - Group Stage: Round 3"
      ]
    },
    {
      "competition": "Türkiye Cup - Group Stage: Round 3",
      "title": "Keçiörengücü v Gaziantep",
      "kickoff_baghdad": "02:00",
      "channels_raw": [
        "A Spor Türkiye HD",
        "SportKlub 1 Hrvatska HD",
        "SportKlub 1 Slovenija HD",
        "Discover more",
        "Fan apparel",
        "Ligue 1 Jerseys",
        "Champions League Merch",
        "Euro Cup tickets",
        "Soccer balls",
        "Sports memorabilia",
        "Sports",
        "Sports betting guides",
        "Motorsport Tickets",
        "Youth Soccer Equipment",
        "L.J.'s LIVE Football on Satellite TV. LiveOnSat.com. LJ-Sport.com. All Rights",
        "Reserved. Copyright (c) 1997 - 2026",
        "Cookie Consent by",
        "Free Privacy Policy Generator website"
      ]
    }
  ]
}